py_rust_regex-0.1.3.dist-info/METADATA
py_rust_regex-0.1.3.dist-info/WHEEL
py_rust_regex-0.1.3.dist-info/license_files/LICENSE
py_rust_regex/__init__.py
py_rust_regex/py_rust_regex.cpython-311-darwin.so
py_rust_regex-0.1.3.dist-info/RECORD
