Metadata-Version: 2.3
Name: py-rust-regex
Version: 0.1.3
Classifier: Programming Language :: Rust
Classifier: Programming Language :: Python :: Implementation :: CPython
Classifier: Programming Language :: Python :: Implementation :: PyPy
Requires-Python: >=3.8
Project-URL: homepage, https://github.com/dttvn0010/py-rust-regex
